axiomathbf/MVFunction.py
axiomathbf/__init__.py
axiomathbf/chainrule.py
axiomathbf/directional_derivative.py
axiomathbf/environment.py
axiomathbf/extrema.py
axiomathbf/gradient.py
axiomathbf/mv_function.py
axiomathbf/parametric_lines.py
axiomathbf/plane.py
axiomathbf/vector_value.py
axiomathbf-0.0.4.dist-info/LICENSE
axiomathbf-0.0.4.dist-info/METADATA
axiomathbf-0.0.4.dist-info/WHEEL
axiomathbf-0.0.4.dist-info/top_level.txt
axiomathbf-0.0.4.dist-info/RECORD
