Metadata-Version: 2.1
Name: axiomathbf
Version: 0.0.4
Summary: Multivariable Calculus Aid
Home-page: https://github.com/AoWangPhilly
Author: Ao Wang
Author-email: aw3338@drexel.edu
License: MIT
Keywords: Python,Multivariable Calculus,Sympy,Latex
Platform: UNKNOWN
Classifier: Development Status :: 3 - Alpha
Classifier: Intended Audience :: Developers
Classifier: Topic :: Software Development :: Build Tools
Classifier: License :: OSI Approved :: MIT License
Classifier: Programming Language :: Python :: 3
Classifier: Programming Language :: Python :: 3.6
Classifier: Programming Language :: Python :: 3.7
